pciSeq/__init__.py
pciSeq/_version.py
pciSeq/app.py
pciSeq/config.py
pciSeq/src/__init__.py
pciSeq/src/core/__init__.py
pciSeq/src/core/datatypes.py
pciSeq/src/core/logger.py
pciSeq/src/core/main.py
pciSeq/src/core/summary.py
pciSeq/src/core/utils.py
pciSeq/src/diagnostics/__init__.py
pciSeq/src/diagnostics/config.py
pciSeq/src/diagnostics/diagnostics.py
pciSeq/src/diagnostics/launch_diagnostics.py
pciSeq/src/diagnostics/utils.py
pciSeq/src/preprocess/__init__.py
pciSeq/src/preprocess/cell_borders.py
pciSeq/src/preprocess/spot_labels.py
pciSeq/src/preprocess/utils.py
pciSeq/src/viewer/__init__.py
pciSeq/src/viewer/run_flask.py
pciSeq/src/viewer/stage_image.py
pciSeq/src/viewer/utils.py
pciSeq/static/2D/index.html
pciSeq/static/2D/viewer/genes_datatable.html
pciSeq/static/2D/viewer/css/index.css
pciSeq/static/2D/viewer/css/progress.css
pciSeq/static/2D/viewer/js/classConfig.js
pciSeq/static/2D/viewer/js/config.js
pciSeq/static/2D/viewer/js/customControl.js
pciSeq/static/2D/viewer/js/dapi.js
pciSeq/static/2D/viewer/js/dataLoader.js
pciSeq/static/2D/viewer/js/donut.js
pciSeq/static/2D/viewer/js/dt.js
pciSeq/static/2D/viewer/js/glyphConfig.js
pciSeq/static/2D/viewer/js/glyphPaths.js
pciSeq/static/2D/viewer/js/glyphs.js
pciSeq/static/2D/viewer/js/index.js
pciSeq/static/2D/viewer/js/progress.js
pciSeq/static/2D/viewer/js/stage_cells.js
pciSeq/static/2D/viewer/js/stage_glyphs.js
pciSeq/static/2D/viewer/js/stage_markers_patched.js
pciSeq/static/2D/viewer/js/stage_polygons.js
pciSeq/static/2D/viewer/js/streaming-tsv-parser.js
pciSeq/static/2D/viewer/js/viewerUtils.js
pciSeq/static/2D/viewer/js/lib/css/L.Control.Layers.Tree.css
pciSeq/static/2D/viewer/js/lib/css/Leaflet.Coordinates-0.1.3.css
pciSeq/static/2D/viewer/js/lib/css/bootstrap.min.css
pciSeq/static/2D/viewer/js/lib/css/index.css
pciSeq/static/2D/viewer/js/lib/css/keen-dashboards.css
pciSeq/static/2D/viewer/js/lib/css/screen.css
pciSeq/static/2D/viewer/js/lib/js/L.Control.Layers.Tree.js
pciSeq-0.0.61.dist-info/LICENCE
pciSeq-0.0.61.dist-info/METADATA
pciSeq-0.0.61.dist-info/WHEEL
pciSeq-0.0.61.dist-info/top_level.txt
pciSeq-0.0.61.dist-info/RECORD
