Metadata-Version: 2.1
Name: pciSeq
Version: 0.0.61
Summary: Probabilistic cell typing for spatial transcriptomics
Home-page: https://github.com/acycliq/pciSeq
Author: Dimitris Nicoloutsopoulos
Author-email: dimitris.nicoloutsopoulos@gmail.com
License: BSD
Classifier: Programming Language :: Python :: 3
Classifier: License :: OSI Approved :: BSD License
Classifier: Operating System :: OS Independent
License-File: LICENCE
Requires-Dist: altair
Requires-Dist: dask
Requires-Dist: diplib
Requires-Dist: fastremap
Requires-Dist: flask
Requires-Dist: natsort
Requires-Dist: numexpr
Requires-Dist: numpy-groupies
Requires-Dist: pandas
Requires-Dist: pyvips
Requires-Dist: redis
Requires-Dist: scikit-image
Requires-Dist: scikit-learn
Requires-Dist: scipy
Requires-Dist: streamlit
Requires-Dist: tomlkit
Requires-Dist: tqdm
Provides-Extra: interactive
Requires-Dist: matplotlib >=2.2.0 ; extra == 'interactive'
Requires-Dist: jupyter ; extra == 'interactive'
